idol/__init__.py
idol/cli.py
idol/freezer.py
idol/harvester.py
idol/heuristics.py
idol/models.py
idol/reviewer.py
idol/utils.py
idol_cli-0.1.0.dist-info/licenses/LICENSE
idol_cli-0.1.0.dist-info/METADATA
idol_cli-0.1.0.dist-info/WHEEL
idol_cli-0.1.0.dist-info/entry_points.txt
idol_cli-0.1.0.dist-info/top_level.txt
idol_cli-0.1.0.dist-info/RECORD
