Metadata-Version: 2.4
Name: idol-cli
Version: 0.1.0
Summary: IDOL - Incremental DAG Optimization for Learning CLI
Author-email: IDOL Team <idol@example.com>
License: MIT
Project-URL: Homepage, https://github.com/dongahn/auto-taskopt
Project-URL: Bug Reports, https://github.com/dongahn/auto-taskopt/issues
Project-URL: Source, https://github.com/dongahn/auto-taskopt
Keywords: machine-learning,data-labeling,golden-dataset,cli
Classifier: Development Status :: 3 - Alpha
Classifier: Intended Audience :: Developers
Classifier: Topic :: Software Development :: Libraries :: Python Modules
Classifier: License :: OSI Approved :: MIT License
Classifier: Programming Language :: Python :: 3
Classifier: Programming Language :: Python :: 3.9
Classifier: Programming Language :: Python :: 3.10
Classifier: Programming Language :: Python :: 3.11
Classifier: Programming Language :: Python :: 3.12
Requires-Python: >=3.9
License-File: LICENSE
Requires-Dist: click>=8.1.0
Requires-Dist: pydantic>=2.0.0
Requires-Dist: ijson>=3.2.0
Provides-Extra: dev
Requires-Dist: pytest>=7.0.0; extra == "dev"
Requires-Dist: pytest-cov>=4.0.0; extra == "dev"
Requires-Dist: ruff>=0.1.0; extra == "dev"
Requires-Dist: mypy>=1.0.0; extra == "dev"
Dynamic: license-file
